kagent_cli/__init__.py
kagent_cli/__main__.py
kagent_cli/client.py
kagent_cli-0.1.9.dist-info/METADATA
kagent_cli-0.1.9.dist-info/WHEEL
kagent_cli-0.1.9.dist-info/entry_points.txt
kagent_cli-0.1.9.dist-info/top_level.txt
kagent_cli-0.1.9.dist-info/RECORD
