Metadata-Version: 2.4
Name: kagent-cli
Version: 0.1.9
Summary: KaioAgent Client (Pure Python)
Home-page: https://github.com/siliconuy/kagent-dev
Author: Silicon UY
Author-email: dev@siliconuy.com
Classifier: Programming Language :: Python :: 3
Classifier: Programming Language :: Python :: 3.8
Classifier: Programming Language :: Python :: 3.9
Classifier: Programming Language :: Python :: 3.10
Classifier: Programming Language :: Python :: 3.11
Classifier: Programming Language :: Python :: 3.12
Classifier: License :: OSI Approved :: MIT License
Classifier: Operating System :: OS Independent
Requires-Python: >=3.7
Requires-Dist: asyncio>=3.4.3
Requires-Dist: websockets>=9.1
Requires-Dist: aiohttp>=3.7.4
Dynamic: author
Dynamic: author-email
Dynamic: classifier
Dynamic: description
Dynamic: description-content-type
Dynamic: home-page
Dynamic: requires-dist
Dynamic: requires-python
Dynamic: summary
